setup.py
email/base64mime.py
email/encoders.py
email/quoprimime.py
micropython_email.encoders.egg-info/PKG-INFO
micropython_email.encoders.egg-info/SOURCES.txt
micropython_email.encoders.egg-info/dependency_links.txt
micropython_email.encoders.egg-info/requires.txt
micropython_email.encoders.egg-info/top_level.txt